README.md
setup.cfg
setup.py
benchupload/__init__.py
benchupload/__main__.py
benchupload/cidetect.py
benchupload/xunit.py
benchupload.egg-info/PKG-INFO
benchupload.egg-info/SOURCES.txt
benchupload.egg-info/dependency_links.txt
benchupload.egg-info/entry_points.txt
benchupload.egg-info/requires.txt
benchupload.egg-info/top_level.txt