Metadata-Version: 1.1
Name: benchupload
Version: 7
Summary: Collect xUnit xml files and upload them to bob-bench.org
Home-page: http://www.bob-bench.org
Author: Holger Hans Peter Freyther
Author-email: help@bob-bench.org
License: AGPLv3+
Download-URL: http://www.bob-bench.org
Platform: UNKNOWN
